CONTRIBUTING.md
LICENSE
MANIFEST.in
README.md
setup.cfg
setup.py
docs/Makefile
docs/conf.py
docs/index.rst
docs/make.bat
docs/_apidoc/metaworlds.core.rst
docs/_apidoc/metaworlds.envs.box2d.parser.rst
docs/_apidoc/metaworlds.envs.box2d.rst
docs/_apidoc/metaworlds.envs.mujoco.gather.rst
docs/_apidoc/metaworlds.envs.mujoco.hill.rst
docs/_apidoc/metaworlds.envs.mujoco.maze.rst
docs/_apidoc/metaworlds.envs.mujoco.randomization.rst
docs/_apidoc/metaworlds.envs.mujoco.rst
docs/_apidoc/metaworlds.envs.rst
docs/_apidoc/metaworlds.misc.logger.rst
docs/_apidoc/metaworlds.misc.rst
docs/_apidoc/metaworlds.rst
docs/_apidoc/metaworlds.spaces.rst
src/metaworlds/__init__.py
src/metaworlds/__version__.py
src/metaworlds/pallet.py
src/metaworlds.egg-info/PKG-INFO
src/metaworlds.egg-info/SOURCES.txt
src/metaworlds.egg-info/dependency_links.txt
src/metaworlds.egg-info/requires.txt
src/metaworlds.egg-info/top_level.txt
src/metaworlds/benchmarks/__init__.py
src/metaworlds/benchmarks/point_mass_suite.py
src/metaworlds/benchmarks/pusher_suite.py
src/metaworlds/core/__init__.py
src/metaworlds/core/parameterized.py
src/metaworlds/core/serializable.py
src/metaworlds/envs/__init__.py
src/metaworlds/envs/base.py
src/metaworlds/envs/env_spec.py
src/metaworlds/envs/grid_world_env.py
src/metaworlds/envs/identification_env.py
src/metaworlds/envs/noisy_env.py
src/metaworlds/envs/occlusion_env.py
src/metaworlds/envs/point_env.py
src/metaworlds/envs/sliding_mem_env.py
src/metaworlds/envs/util.py
src/metaworlds/envs/box2d/__init__.py
src/metaworlds/envs/box2d/box2d_env.py
src/metaworlds/envs/box2d/box2d_viewer.py
src/metaworlds/envs/box2d/car_parking_env.py
src/metaworlds/envs/box2d/cartpole_swingup_env.py
src/metaworlds/envs/box2d/parser/__init__.py
src/metaworlds/envs/box2d/parser/xml_attr_types.py
src/metaworlds/envs/box2d/parser/xml_box2d.py
src/metaworlds/envs/box2d/parser/xml_types.py
src/metaworlds/envs/mujoco/__init__.py
src/metaworlds/envs/mujoco/ant_env.py
src/metaworlds/envs/mujoco/half_cheetah_env.py
src/metaworlds/envs/mujoco/hopper_env.py
src/metaworlds/envs/mujoco/mujoco_env.py
src/metaworlds/envs/mujoco/point_env.py
src/metaworlds/envs/mujoco/simple_humanoid_env.py
