Metadata-Version: 2.1
Name: metaworlds
Version: 0.0.1.dev0
Summary: Environments for benchmarking meta-learning and multi-task learning
Home-page: https://github.com/rlworkgroup/metaworlds
Author: Reinforcement Learning Working Group
License: MIT
Platform: UNKNOWN
Classifier: Development Status :: 4 - Beta
Classifier: Intended Audience :: Developers
Classifier: Intended Audience :: Education
Classifier: Intended Audience :: Science/Research
Classifier: License :: OSI Approved :: MIT License
Classifier: Programming Language :: Python :: 3.5
Classifier: Programming Language :: Python :: 3.6
Classifier: Programming Language :: Python :: 3.7
Classifier: Programming Language :: Python :: 3 :: Only
Classifier: Topic :: Scientific/Engineering :: Artificial Intelligence
Classifier: Topic :: Scientific/Engineering :: Mathematics
Classifier: Topic :: Software Development :: Libraries
Provides-Extra: box2d
Provides-Extra: all
Provides-Extra: dev
Provides-Extra: mujoco
